prettytask.py
prettytask-0.0.2.dist-info/DESCRIPTION.rst
prettytask-0.0.2.dist-info/METADATA
prettytask-0.0.2.dist-info/RECORD
prettytask-0.0.2.dist-info/WHEEL
prettytask-0.0.2.dist-info/metadata.json
prettytask-0.0.2.dist-info/top_level.txt
