Metadata-Version: 2.0
Name: prettytask
Version: 0.0.2
Summary: Pretty task printing
Home-page: http://github.com/jomag/prettytask
Author: Jonatan Magnusson
Author-email: jonatan.magnusson@gmail.com
License: MIT
Keywords: cli commandline prompt
Platform: UNKNOWN
Classifier: Development Status :: 3 - Alpha
Classifier: Intended Audience :: Developers
Classifier: License :: OSI Approved :: MIT License
Classifier: Programming Language :: Python :: 2
Classifier: Programming Language :: Python :: 3
Requires-Dist: colorama
